package/__init__.py
package/calculator.py
package/greet.py
test_gaa_test-0.1.0.dist-info/METADATA
test_gaa_test-0.1.0.dist-info/WHEEL
test_gaa_test-0.1.0.dist-info/top_level.txt
test_gaa_test-0.1.0.dist-info/RECORD
