Metadata-Version: 2.1
Name: test-gaa-test
Version: 0.1.0
Summary: A simple Python package with calculator and greeting functions.
Home-page: https://github.com/yourusername/my_package
Author: Your Name
Author-email: your.email@example.com
Classifier: Programming Language :: Python :: 3
Classifier: License :: OSI Approved :: MIT License
Classifier: Operating System :: OS Independent
Requires-Python: >=3.6
